story_chilren_gemma3/__init__.py
story_chilren_gemma3/config/config.json
story_chilren_gemma3/textToHistory.py
story_chilren_gemma3/utils/__init__.py
story_chilren_gemma3/utils/setup.py
story_chilren_gemma3-0.1.21.dist-info/METADATA
story_chilren_gemma3-0.1.21.dist-info/WHEEL
story_chilren_gemma3-0.1.21.dist-info/RECORD
