Metadata-Version: 2.3
Name: story-chilren-gemma3
Version: 0.1.21
Summary: Prompt programável para geração de histórias infantis pensado para videos no youtube de 1 minuto
Author: William Ferreira
Author-email: 33575357+illiamw@users.noreply.github.com
Requires-Python: >=3.11
Classifier: Programming Language :: Python :: 3
Classifier: Programming Language :: Python :: 3.11
Classifier: Programming Language :: Python :: 3.12
Classifier: Programming Language :: Python :: 3.13
Requires-Dist: ollama (>=0.4.7,<0.5.0) ; python_version >= "3.11" and python_version < "4.0"
Requires-Dist: regex (>=2024.11.6,<2025.0.0)
Requires-Dist: tqdm (>=4.67.1,<5.0.0)
